CHANGES.rst
MANIFEST.in
README.rst
setup.cfg
setup.py
src/iocdoc/LICENSE
src/iocdoc/__init__.py
src/iocdoc/_version.py
src/iocdoc/command_file.py
src/iocdoc/database.py
src/iocdoc/ioc.py
src/iocdoc/macros.py
src/iocdoc/record.py
src/iocdoc/reports.py
src/iocdoc/template.py
src/iocdoc/text_file.py
src/iocdoc/token_support.py
src/iocdoc/utils.py
src/iocdoc.egg-info/PKG-INFO
src/iocdoc.egg-info/SOURCES.txt
src/iocdoc.egg-info/dependency_links.txt
src/iocdoc.egg-info/entry_points.txt
src/iocdoc.egg-info/requires.txt
src/iocdoc.egg-info/top_level.txt