Metadata-Version: 1.1
Name: iocdoc
Version: 0.0.2
Summary: Document the configuration of an EPICS IOC
Home-page: http://iocdoc.readthedocs.org
Author: Pete R. Jemian
Author-email: jemian@anl.gov
License: UChicago Argonne, LLC OPEN SOURCE LICENSE (see LICENSE file)
Download-URL: https://github.com/prjemian/iocdoc.git
Keywords: APS,EPICS,IOC
Platform: any
Classifier: Development Status :: 5 - Production/Stable
Classifier: Environment :: Console
Classifier: Intended Audience :: Science/Research
Classifier: License :: Free To Use But Restricted
Classifier: Operating System :: OS Independent
Classifier: Programming Language :: Python
Classifier: Topic :: Scientific/Engineering
Classifier: Topic :: Utilities
